<?xml version="1.0" encoding="UTF-8"?>
<npc name="Ivan" script="addons/ivan.lua" walkinterval="2000" floorchange="0" speechbubble="0" skull="green">
	<health now="100" max="100" />
	<look type="684" head="57" body="59" legs="40" feet="76" addons="1" />
	<parameters>
		<parameter key="message_greet" value="Hello |PLAYERNAME|. I sell munitions. Say {trade}. And have other {jobs}." />
		<parameter key="message_decline" value="Is |TOTALCOST| gold coins too much for you? Get out of here!" />
		<parameter key="module_shop" value="1" />
		<parameter key="shop_sellable" value="
			assassin stars,29059,75;
			assassin stars,7368,50;
			leaf star, 29036, 40;

			badger boots, 24742, 7500;
			fur armor, 24741, 5000;

			crossbow,2455,150;
			bow,2456,130;
			minotaur trophy, 7401, 500;
			lizard trophy, 11336, 8000;
			cyclops trophy, 7398, 500;
			draken trophy, 11315, 15000;
			bonebeast trophy, 11161, 6000;
			deer trophy, 7397, 3000;
			lion trophy, 7400, 3000;
			orc trophy, 7395, 1000;
			wolf trophy, 7394, 1000;
			behemoth trophy, 7396, 20000;
			demon trophy, 7393, 40000;
			dragon lord trophy, 7399, 10000;" />
		<parameter key="shop_buyable" value="
			assassin stars,29059,150;
			assassin stars,7368,100;
			leaf star, 29036, 80;

			arrow,2544,3;
			bolt,2543,4;
			bow,2456,400;
			crossbow,2455,500;
			crystalline arrow,18304,20;
			drill bolt,18436,12;
			earth arrow,7850,5;
			envenomed arrow,18437,12;
			flaming arrow,7840,5;
			flash arrow,7838,5;
			onyx arrow,7365,7;
			piercing bolt,7363,5;
			power bolt,2547,7;
			prismatic bolt,18435,20;
			shiver arrow,7839,5;
			sniper arrow,7364,5;
			spear,2389,9;
			tarsal arrow,15648,6;
			throwing knife,2410,25;
			throwing star,2399,42;
			vortex bolt,15649,6" />
	</parameters>
</npc>
